pocket_tts/__init__.py
pocket_tts/__main__.py
pocket_tts/default_parameters.py
pocket_tts/main.py
pocket_tts/conditioners/__init__.py
pocket_tts/conditioners/base.py
pocket_tts/conditioners/text.py
pocket_tts/config/b6369a24.yaml
pocket_tts/data/__init__.py
pocket_tts/data/audio.py
pocket_tts/data/audio_utils.py
pocket_tts/models/__init__.py
pocket_tts/models/flow_lm.py
pocket_tts/models/mimi.py
pocket_tts/models/tts_model.py
pocket_tts/modules/__init__.py
pocket_tts/modules/conv.py
pocket_tts/modules/dummy_quantizer.py
pocket_tts/modules/layer_scale.py
pocket_tts/modules/mimi_transformer.py
pocket_tts/modules/mlp.py
pocket_tts/modules/resample.py
pocket_tts/modules/rope.py
pocket_tts/modules/seanet.py
pocket_tts/modules/stateful_module.py
pocket_tts/modules/transformer.py
pocket_tts/static/index.html
pocket_tts/utils/__init__.py
pocket_tts/utils/config.py
pocket_tts/utils/debugging.py
pocket_tts/utils/logging_utils.py
pocket_tts/utils/utils.py
pocket_tts/utils/weights_loading.py
pocket_tts-1.0.3.dist-info/METADATA
pocket_tts-1.0.3.dist-info/WHEEL
pocket_tts-1.0.3.dist-info/entry_points.txt
pocket_tts-1.0.3.dist-info/licenses/LICENSE
pocket_tts-1.0.3.dist-info/RECORD
