Metadata-Version: 2.4
Name: pocket-tts
Version: 1.0.3
Summary: Kyutai's pocket-sized text-to-speech!
License-File: LICENSE
Requires-Python: <3.15,>=3.10
Requires-Dist: beartype>=0.22.5
Requires-Dist: einops>=0.4.0
Requires-Dist: fastapi>=0.100
Requires-Dist: huggingface-hub>=0.10
Requires-Dist: numpy>=2
Requires-Dist: pydantic>=2
Requires-Dist: python-multipart>=0.0.21
Requires-Dist: requests>=2.20.0
Requires-Dist: safetensors>=0.4.0
Requires-Dist: scipy>=1.5.0
Requires-Dist: sentencepiece>=0.2.1
Requires-Dist: torch>=2.5.0
Requires-Dist: typer>=0.10.0
Requires-Dist: typing-extensions>=4.0.0
Requires-Dist: uvicorn>=0.13.0
Provides-Extra: audio
Requires-Dist: soundfile>=0.12.0; extra == 'audio'
